ynab_mcp/__init__.py
ynab_mcp/config.py
ynab_mcp/server.py
ynab_mcp/ynab.py
ynab_mcp-0.1.0.dist-info/METADATA
ynab_mcp-0.1.0.dist-info/WHEEL
ynab_mcp-0.1.0.dist-info/entry_points.txt
ynab_mcp-0.1.0.dist-info/licenses/LICENSE
ynab_mcp-0.1.0.dist-info/RECORD
