Metadata-Version: 2.4
Name: ynab-mcp
Version: 0.1.0
Summary: A Model Context Protocol server for interacting with YNAB
License: MIT
License-File: LICENSE
Requires-Python: >=3.13
Requires-Dist: fastmcp>=0.2.0
Requires-Dist: httpx>=0.26.0
Requires-Dist: pydantic>=2.0.0
Requires-Dist: python-dotenv>=1.0.0
